url_normalize/__init__.py
url_normalize/cli.py
url_normalize/generic_url_cleanup.py
url_normalize/normalize_fragment.py
url_normalize/normalize_host.py
url_normalize/normalize_path.py
url_normalize/normalize_port.py
url_normalize/normalize_query.py
url_normalize/normalize_scheme.py
url_normalize/normalize_userinfo.py
url_normalize/param_allowlist.py
url_normalize/provide_url_scheme.py
url_normalize/tools.py
url_normalize/url_normalize.py
url_normalize-2.1.0.dist-info/licenses/LICENSE
url_normalize-2.1.0.dist-info/METADATA
url_normalize-2.1.0.dist-info/WHEEL
url_normalize-2.1.0.dist-info/entry_points.txt
url_normalize-2.1.0.dist-info/top_level.txt
url_normalize-2.1.0.dist-info/RECORD
