Metadata-Version: 2.4
Name: url-normalize
Version: 2.1.0
Summary: URL normalization for Python
Author-email: Nikolay Panov <github@npanov.com>
License: MIT
Project-URL: Homepage, https://github.com/niksite/url-normalize
Project-URL: Repository, https://github.com/niksite/url-normalize
Project-URL: Issues, https://github.com/niksite/url-normalize/issues
Project-URL: Changelog, https://github.com/niksite/url-normalize/blob/master/CHANGELOG.md
Keywords: url,normalization,normalize
Requires-Python: >=3.8
License-File: LICENSE
Requires-Dist: idna>=3.3
Provides-Extra: dev
Requires-Dist: mypy; extra == "dev"
Requires-Dist: pre-commit; extra == "dev"
Requires-Dist: pytest-cov; extra == "dev"
Requires-Dist: pytest-ruff; extra == "dev"
Requires-Dist: pytest-socket; extra == "dev"
Requires-Dist: pytest; extra == "dev"
Requires-Dist: ruff; extra == "dev"
Requires-Dist: tox; extra == "dev"
Dynamic: license-file
